fast_script_utils/__init__.py
fast_script_utils/crawler.py
fast_script_utils/file.py
fast_script_utils/sweet.py
fast_script_utils/time.py
fast_script_utils-0.1.6.dist-info/METADATA
fast_script_utils-0.1.6.dist-info/WHEEL
fast_script_utils-0.1.6.dist-info/top_level.txt
fast_script_utils-0.1.6.dist-info/RECORD
