Metadata-Version: 2.1
Name: fast_script_utils
Version: 0.1.6
Requires-Dist: requests
Requires-Dist: lxml
